{
  "$schema": "https://unpkg.com/knip@5/schema.json",
  "rules": {
    "types": "off",
    "enumMembers": "off",
    "files": "off",
    "exports": "off",
    "duplicates": "off",
    "classMembers": "error",
    "nsTypes": "error",
    "unresolved": "error",
    "nsExports": "error",
    "unlisted": "error",
    "binaries": "off",
    "optionalPeerDependencies": "error",
    "dependencies": "error",
    "devDependencies": "error"
  },
  "ignore": ["playwright/**", "**/*.js"],
  "ignoreDependencies": [
    "@graphql-codegen/typescript-apollo-client-helpers",
    "@graphql-codegen/typescript-operations",
    "@graphql-codegen/typescript-react-apollo",
    "@graphql-codegen/add",
    "@graphql-codegen/fragment-matcher",
    "@graphql-codegen/import-types-preset",
    "@graphql-codegen/typescript",
    "@material-ui/styles",
    "keycode",
    "tslib",
    "@swc/jest",
    "@types/lodash-es",
    "@types/webappsec-credential-management",
    "core-js",
    "identity-obj-proxy",
    "moment",
    "history",
    "react-transition-group",
    "@radix-ui/react-radio-group",
    "@react-editor-js/core",
    "@radix-ui/react-portal",
    "@graphql-codegen/schema-ast",
    "playwright-testmo-reporter",
    "mocha",
    "mochawesome",
    "mochawesome-report-generator",
    "mochawesome-merge"
  ]
}
